textsearchpy/__init__.py
textsearchpy/exception.py
textsearchpy/index.py
textsearchpy/normalizers.py
textsearchpy/query.py
textsearchpy/tokenizers.py
textsearchpy-1.2.0.dist-info/METADATA
textsearchpy-1.2.0.dist-info/WHEEL
textsearchpy-1.2.0.dist-info/licenses/LICENSE
textsearchpy-1.2.0.dist-info/RECORD
